LICENSE
README.md
git_t5/__init__.py
git_t5/cli/__init__.py
git_t5/cli/conf/__init__.py
git_t5/cli/conf/config.yaml
git_t5/cli/conf/config_model.yaml
git_t5/cli/conf/config_tokenizer.yaml
git_t5/cli/conf/data/huggingface.yaml
git_t5/cli/conf/dataset/default.yaml
git_t5/cli/conf/dataset/huggingface.yaml
git_t5/cli/conf/dataset/local.yaml
git_t5/cli/conf/dataset/multitask.yaml
git_t5/cli/conf/logger/wandb.yaml
git_t5/cli/conf/model/huggingface.yaml
git_t5/cli/conf/optimizer/adafactor.yaml
git_t5/cli/conf/optimizer/adagrad.yaml
git_t5/cli/conf/optimizer/adam.yaml
git_t5/cli/conf/optimizer/adamw.yaml
git_t5/cli/conf/optimizer/scheduler/constant.yaml
git_t5/cli/conf/optimizer/scheduler/inverse_square_root.yaml
git_t5/cli/conf/optimizer/scheduler/linear.yaml
git_t5/cli/conf/optimizer/scheduler/polynomial.yaml
git_t5/cli/conf/tokenizer/huggingface.yaml
git_t5/cli/conf/tokenizer_trainer/sentencepiece.yaml
git_t5/cli/conf/tokenizer_trainer/tokenizer/sentencepiece.yaml
git_t5/cli/conf/trainer/huggingface.yaml
git_t5/cli/conf/training/default.yaml
git_t5/cli/config.py
git_t5/cli/train_model.py
git_t5/cli/train_tokenizer.py
git_t5/core/__init__.py
git_t5/core/configs/__init__.py
git_t5/core/configs/config.py
git_t5/core/configs/dataset.py
git_t5/core/configs/tokenizer.py
git_t5/core/configs/training.py
git_t5/core/data_module.py
git_t5/core/logger.py
git_t5/core/model.py
git_t5/core/optimizers.py
git_t5/core/schedulers.py
git_t5/core/tokenizer_model.py
git_t5/core/tokenizer_trainer.py
git_t5/core/trainer.py
git_t5/data/__init__.py
git_t5/data/data_collator.py
git_t5/data/data_preprocessing.py
git_t5/data/dataset.py
git_t5/tests/__init__.py
git_t5/utils/__init__.py
git_t5/utils/code_tools/__init__.py
git_t5/utils/code_tools/diffgen.py
git_t5/utils/code_tools/html_stripper.py
git_t5/utils/code_tools/tokenizer.py
git_t5/utils/common.py
git_t5/utils/distributed.py
git_t5/utils/resolvers.py
git_t5-0.2.4.dist-info/entry_points.txt
git_t5-0.2.4.dist-info/LICENSE
git_t5-0.2.4.dist-info/WHEEL
git_t5-0.2.4.dist-info/METADATA
git_t5-0.2.4.dist-info/RECORD
